jysnowball/__init__.py
jysnowball/api_ref.py
jysnowball/bond.py
jysnowball/capital.py
jysnowball/cons.py
jysnowball/cube.py
jysnowball/f10.py
jysnowball/finance.py
jysnowball/fund.py
jysnowball/hkex.py
jysnowball/index.py
jysnowball/realtime.py
jysnowball/report.py
jysnowball/token.py
jysnowball/u.py
jysnowball/user.py
jysnowball/utls.py
jysnowball_v2/__init__.py
jysnowball_v2/api_ref.py
jysnowball_v2/bond.py
jysnowball_v2/capital.py
jysnowball_v2/cons.py
jysnowball_v2/cube.py
jysnowball_v2/f10.py
jysnowball_v2/finance.py
jysnowball_v2/fund.py
jysnowball_v2/hkex.py
jysnowball_v2/index.py
jysnowball_v2/realtime.py
jysnowball_v2/report.py
jysnowball_v2/token.py
jysnowball_v2/u.py
jysnowball_v2/user.py
jysnowball_v2/utls.py
tests/__init__.py
yzwsnowball/__init__.py
yzwsnowball/api_ref.py
yzwsnowball/bond.py
yzwsnowball/capital.py
yzwsnowball/cons.py
yzwsnowball/cube.py
yzwsnowball/f10.py
yzwsnowball/finance.py
yzwsnowball/fund.py
yzwsnowball/hkex.py
yzwsnowball/index.py
yzwsnowball/realtime.py
yzwsnowball/report.py
yzwsnowball/token.py
yzwsnowball/u.py
yzwsnowball/user.py
yzwsnowball/utls.py
yzwsnowball-0.5.dist-info/METADATA
yzwsnowball-0.5.dist-info/WHEEL
yzwsnowball-0.5.dist-info/top_level.txt
yzwsnowball-0.5.dist-info/RECORD
