Metadata-Version: 2.1
Name: yzwsnowball
Version: 0.5
Summary: A brief description of your package
Home-page: https://github.com/yzw2010/jysnowball/
Author: JY Yu Chi Wai
Author-email: 13715416@qq.com
Classifier: Programming Language :: Python :: 3
Classifier: License :: OSI Approved :: MIT License
Classifier: Operating System :: OS Independent
Requires-Python: >=3.6
